setup.py
efacter/Facter.py
efacter/__init__.py
efacter/efacter.py
efacter.egg-info/PKG-INFO
efacter.egg-info/SOURCES.txt
efacter.egg-info/dependency_links.txt
efacter.egg-info/entry_points.txt
efacter.egg-info/requires.txt
efacter.egg-info/top_level.txt