Metadata-Version: 1.0
Name: efacter
Version: 0.1.2
Summary: facter client with extended functionality and Facter class to work with complex facts
Home-page: http://github.com/CSXbot/efacter
Author: Mikhail Tuzikov
Author-email: tuzikov@gmail.com
License: Creative Commons Attribution 4.0 International License
Keywords: facter puppet
Platform: UNKNOWN
